rtfd/__init__.py
rtfd/_cli.py
rtfd/_log.py
rtfd/api.py
rtfd/app.py
rtfd/config.py
rtfd/exceptions.py
rtfd/libs.py
rtfd/utils.py
rtfd/scripts/builder.sh
rtfd/static/rtfd.js
rtfd/static/tipped.css
rtfd/static/tipped.js
rtfd-0.4.5.dist-info/LICENSE
rtfd-0.4.5.dist-info/METADATA
rtfd-0.4.5.dist-info/WHEEL
rtfd-0.4.5.dist-info/entry_points.txt
rtfd-0.4.5.dist-info/top_level.txt
rtfd-0.4.5.dist-info/RECORD
