Metadata-Version: 2.1
Name: rtfd
Version: 0.4.5
Summary: Build, read your exclusive and fuck docs.
Home-page: https://github.com/staugur/rtfd
Author: staugur
Author-email: staugur@saintic.com
License: BSD 3-Clause
Download-URL: https://github.com/staugur/rtfd/releases/tag/0.4.5
Project-URL: Code, https://github.com/staugur/rtfd
Project-URL: Issue tracker, https://github.com/staugur/rtfd/issues
Project-URL: Documentation, https://docs.saintic.com/rtfd/
Keywords: docs,sphinx,reStructuredText
Platform: UNKNOWN
Classifier: Development Status :: 4 - Beta
Classifier: Environment :: Console
Classifier: Intended Audience :: Developers
Classifier: License :: OSI Approved :: BSD License
Classifier: Programming Language :: Python :: 2.7
Classifier: Programming Language :: Python :: 3.5
Classifier: Programming Language :: Python :: 3.6
Classifier: Programming Language :: Python :: 3.7
Classifier: Programming Language :: Python :: Implementation :: CPython
Classifier: Programming Language :: Python :: Implementation :: PyPy
Classifier: Topic :: Software Development :: Libraries :: Python Modules
Requires-Python: >=2.7, !=3.0.*, !=3.1.*, !=3.2.*, !=3.3.*, !=3.4.*
Requires-Dist: Flask-PluginKit (>=3.5.0)
Requires-Dist: Click (>=7.0)
Requires-Dist: configparser
